histoslice/__init__.py
histoslice/_backend.py
histoslice/_data.py
histoslice/_reader.py
histoslice/cli/_app.py
histoslice/cli/_models.py
histoslice/cli/_options.py
histoslice/functional/__init__.py
histoslice/functional/_check.py
histoslice/functional/_concurrent.py
histoslice/functional/_dearray.py
histoslice/functional/_draw.py
histoslice/functional/_images.py
histoslice/functional/_level.py
histoslice/functional/_mean_std.py
histoslice/functional/_metrics.py
histoslice/functional/_normalize.py
histoslice/functional/_tiles.py
histoslice/functional/_tissue.py
histoslice/utils/__init__.py
histoslice/utils/_normalize.py
histoslice/utils/_process.py
histoslice/utils/_torch.py
histoslice-0.4.0.dist-info/METADATA
histoslice-0.4.0.dist-info/WHEEL
histoslice-0.4.0.dist-info/entry_points.txt
histoslice-0.4.0.dist-info/licenses/LICENSE
histoslice-0.4.0.dist-info/licenses/NOTICE.md
histoslice-0.4.0.dist-info/RECORD
