Metadata-Version: 2.4
Name: histoslice
Version: 0.4.0
Summary: Read and process histological slide images with python!
Project-URL: Homepage, https://github.com/rmuraix/HistoSlice
Project-URL: Documentation, https://lab.rmurai.com/HistoSlice/
Project-URL: Repository, https://github.com/rmuraix/HistoSlice.git
Project-URL: Issues, https://github.com/rmuraix/HistoSlice/issues
Project-URL: Changelog, https://github.com/rmuraix/HistoSlice/releases
Author-email: Ryota Murai <opensource@rmurai.com>
License-Expression: MIT
License-File: LICENSE
License-File: NOTICE.md
Keywords: WSI,Whole Slide Imaging,histology,image processing,slide
Classifier: Development Status :: 4 - Beta
Classifier: Intended Audience :: Science/Research
Classifier: License :: OSI Approved :: MIT License
Classifier: Natural Language :: English
Classifier: Programming Language :: Python :: 3.10
Classifier: Programming Language :: Python :: 3.11
Classifier: Programming Language :: Python :: 3.12
Classifier: Topic :: Scientific/Engineering
Requires-Python: >=3.10
Requires-Dist: aicspylibczi<4,>=3
Requires-Dist: matplotlib
Requires-Dist: mpire>=2.6
Requires-Dist: numpy>=2
Requires-Dist: opencv-python-headless>=4
Requires-Dist: openslide-bin>=4.0.0.2
Requires-Dist: openslide-python>=1.4
Requires-Dist: pillow>=10
Requires-Dist: polars>=1.0
Requires-Dist: pydantic>=2.10.0
Requires-Dist: pyvips[binary]>=3.0.0
Requires-Dist: rich>=14.0.0
Requires-Dist: scikit-learn<2,>=1
Requires-Dist: scipy>=1.10
Requires-Dist: tqdm>=4.66.0
Requires-Dist: typer-di>=0.1.0
Requires-Dist: typer>=0.16.0
